dj_materialized_views/__init__.py
dj_materialized_views/apps.py
dj_materialized_views/tasks.py
dj_materialized_views/utils.py
dj_materialized_views/admin/__init__.py
dj_materialized_views/admin/actions.py
dj_materialized_views/admin/admin.py
dj_materialized_views/migrations/0001_initial.py
dj_materialized_views/migrations/__init__.py
dj_materialized_views/models/__init__.py
dj_materialized_views/models/materialized_view.py
dj_materialized_views/models/materialized_view_index.py
dj_materialized_views/tests/__init__.py
dj_materialized_views/tests/tests.py
dj_materialized_views-0.4.1.dist-info/LICENSE
dj_materialized_views-0.4.1.dist-info/METADATA
dj_materialized_views-0.4.1.dist-info/WHEEL
dj_materialized_views-0.4.1.dist-info/top_level.txt
dj_materialized_views-0.4.1.dist-info/RECORD
